flagpy/__init__.py
flagpy/flag_df.csv
flagpy/flag_identifier.py
flagpy/flag_util.py
flagpy/flags/Afghanistan.pkl
flagpy/flags/Albania.pkl
flagpy/flags/Algeria.pkl
flagpy/flags/Andorra.pkl
flagpy/flags/Angola.pkl
flagpy/flags/Antigua_And_Barbuda.pkl
flagpy/flags/Argentina.pkl
flagpy/flags/Armenia.pkl
flagpy/flags/Australia.pkl
flagpy/flags/Austria.pkl
flagpy/flags/Azerbaijan.pkl
flagpy/flags/Bahrain.pkl
flagpy/flags/Bangladesh.pkl
flagpy/flags/Barbados.pkl
flagpy/flags/Belarus.pkl
flagpy/flags/Belgium.pkl
flagpy/flags/Belize.pkl
flagpy/flags/Benin.pkl
flagpy/flags/Bhutan.pkl
flagpy/flags/Bolivia.pkl
flagpy/flags/Bosnia_And_Herzegovina.pkl
flagpy/flags/Botswana.pkl
flagpy/flags/Brazil.pkl
flagpy/flags/Brunei.pkl
flagpy/flags/Bulgaria.pkl
flagpy/flags/Burkina_Faso.pkl
flagpy/flags/Burundi.pkl
flagpy/flags/Cambodia.pkl
flagpy/flags/Cameroon.pkl
flagpy/flags/Canada.pkl
flagpy/flags/Cape_Verde.pkl
flagpy/flags/Chad.pkl
flagpy/flags/Chile.pkl
flagpy/flags/China.pkl
flagpy/flags/Colombia.pkl
flagpy/flags/Costa_Rica.pkl
flagpy/flags/Croatia.pkl
flagpy/flags/Cuba.pkl
flagpy/flags/Cyprus.pkl
flagpy/flags/Denmark.pkl
flagpy/flags/Djibouti.pkl
flagpy/flags/Dominica.pkl
flagpy/flags/East_Timor.pkl
flagpy/flags/Ecuador.pkl
flagpy/flags/Egypt.pkl
flagpy/flags/El_Salvador.pkl
flagpy/flags/Equatorial_Guinea.pkl
flagpy/flags/Eritrea.pkl
flagpy/flags/Estonia.pkl
flagpy/flags/Eswatini.pkl
flagpy/flags/Ethiopia.pkl
flagpy/flags/Fiji.pkl
flagpy/flags/Finland.pkl
flagpy/flags/France.pkl
flagpy/flags/Gabon.pkl
flagpy/flags/Georgia_(Country).pkl
flagpy/flags/Germany.pkl
flagpy/flags/Ghana.pkl
flagpy/flags/Greece.pkl
flagpy/flags/Grenada.pkl
flagpy/flags/Guatemala.pkl
flagpy/flags/Guinea-Bissau.pkl
flagpy/flags/Guinea.pkl
flagpy/flags/Guyana.pkl
flagpy/flags/Haiti.pkl
flagpy/flags/Honduras.pkl
flagpy/flags/Hungary.pkl
flagpy/flags/Iceland.pkl
flagpy/flags/India.pkl
flagpy/flags/Indonesia.pkl
flagpy/flags/Iran.pkl
flagpy/flags/Iraq.pkl
flagpy/flags/Ireland.pkl
flagpy/flags/Israel.pkl
flagpy-1.0.2.dist-info/LICENSE.txt
flagpy-1.0.2.dist-info/METADATA
flagpy-1.0.2.dist-info/WHEEL
flagpy-1.0.2.dist-info/top_level.txt
flagpy-1.0.2.dist-info/RECORD
