Metadata-Version: 2.1
Name: flagpy
Version: 1.0.2
Summary: Country Flag Classifier.
Home-page: https://github.com/saahilkumar/world-flag-identifier
Author: Saahil Kumar
Author-email: kumar.saa@northeastern.edu
License: MIT
Platform: UNKNOWN
Classifier: License :: OSI Approved :: MIT License
Classifier: Operating System :: OS Independent
Classifier: Programming Language :: Python :: 3
Requires-Dist: Pillow
Requires-Dist: requests
Requires-Dist: numpy
Requires-Dist: pandas
Requires-Dist: ImageHash
Requires-Dist: scikit-image
